tcp_port_checker/__init__.py
tcp_port_checker/__main__.py
tcp_port_checker/config.py
tcp_port_checker/main.py
tcp_port_checker/network_checker.py
tcp_port_checker/report_generator.py
tcp_port_checker/system_monitor.py
tcp_port_checker-1.0.2.dist-info/licenses/LICENSE.txt
tcp_port_checker-1.0.2.dist-info/METADATA
tcp_port_checker-1.0.2.dist-info/WHEEL
tcp_port_checker-1.0.2.dist-info/entry_points.txt
tcp_port_checker-1.0.2.dist-info/top_level.txt
tcp_port_checker-1.0.2.dist-info/RECORD
