Metadata-Version: 2.4
Name: tcp-port-checker
Version: 1.0.2
Summary: A powerful network connectivity analyzer with real-time system monitoring and IPv6 support
Home-page: https://github.com/ismailTrk/tcp-port-checker
Author: iturkyilmazoglu
Author-email: ismail.turkyilmazoglu@gmail.com
Project-URL: Bug Reports, https://github.com/ismailTrk/tcp-port-checker/issues
Project-URL: Source, https://github.com/ismailTrk/tcp-port-checker
Project-URL: Documentation, https://github.com/ismailTrk/tcp-port-checker#readme
Keywords: network,tcp,port,checker,ping,monitoring,connectivity,scanner
Classifier: Development Status :: 5 - Production/Stable
Classifier: Intended Audience :: System Administrators
Classifier: Intended Audience :: Developers
Classifier: Topic :: System :: Networking
Classifier: Topic :: System :: Systems Administration
Classifier: Topic :: Utilities
Classifier: License :: OSI Approved :: MIT License
Classifier: Programming Language :: Python :: 3
Classifier: Programming Language :: Python :: 3.6
Classifier: Programming Language :: Python :: 3.7
Classifier: Programming Language :: Python :: 3.8
Classifier: Programming Language :: Python :: 3.9
Classifier: Programming Language :: Python :: 3.10
Classifier: Programming Language :: Python :: 3.11
Classifier: Operating System :: OS Independent
Classifier: Environment :: Console
Requires-Python: >=3.6
License-File: LICENSE.txt
Dynamic: author
Dynamic: author-email
Dynamic: classifier
Dynamic: description
Dynamic: description-content-type
Dynamic: home-page
Dynamic: keywords
Dynamic: license-file
Dynamic: project-url
Dynamic: requires-python
Dynamic: summary
